{"Head":{"ServerTime":"2021-06-12T13:16:44","ServerType":"Test","ResponseType":"GetHotels","ExecutionTime":"0.03"},"Body":{"HotelsReturned":"263","Hotels":{"Hotel":[{"HotelId":"1127438","CityId":"129601","HotelName":"Golden Palace"},{"HotelId":"1406459","CityId":"129601","HotelName":"Rixos Almaty"},{"HotelId":"1425109","CityId":"129601","HotelName":"Renion"},{"HotelId":"1590741","CityId":"129601","HotelName":"Renion Residence"},{"HotelId":"1664925","CityId":"129601","HotelName":"Kazakhstan"},{"HotelId":"1669945","CityId":"129601","HotelName":"The Ritz-Carlton Almaty"},{"HotelId":"1864640","CityId":"129601","HotelName":"Almaty Hotel"},{"HotelId":"1997130","CityId":"129601","HotelName":"Soluxe"},{"HotelId":"2067333","CityId":"129601","HotelName":"Grand Tien Shan"},{"HotelId":"2105813","CityId":"129601","HotelName":"Royal Tulip Almaty"},{"HotelId":"2146269","CityId":"129601","HotelName":"Ambassador Almaty"},{"HotelId":"2337870","CityId":"129601","HotelName":"Dimal Hostel Almaty"},{"HotelId":"2371795","CityId":"129601","HotelName":"Otrar Hotel"},{"HotelId":"2413581","CityId":"129601","HotelName":"Grand Aiser"},{"HotelId":"2848908","CityId":"129601","HotelName":"Royal Park"},{"HotelId":"2862360","CityId":"129601","HotelName":"Royal Petrol"},{"HotelId":"2937612","CityId":"129601","HotelName":"Best Western Plus Atakent Park Hotel"},{"HotelId":"3069268","CityId":"129601","HotelName":"Royal Palace Hotel"},{"HotelId":"3255322","CityId":"129601","HotelName":"Dostyk"},{"HotelId":"3263159","CityId":"129601","HotelName":"Mildom Apartments"},{"HotelId":"3266484","CityId":"129601","HotelName":"Parasat Hotel & Residence"},{"HotelId":"3268444","CityId":"129601","HotelName":"Kazzhol Almaty"},{"HotelId":"3404336","CityId":"129601","HotelName":"Voyage Almaty"},{"HotelId":"3438470","CityId":"129601","HotelName":"Holiday Inn Almaty"},{"HotelId":"3755503","CityId":"129601","HotelName":"Premier Alatau Hotel & Business Center"},{"HotelId":"3862598","CityId":"129601","HotelName":"Astana International Hotel"},{"HotelId":"3911918","CityId":"129601","HotelName":"Worldhotel Saltanat"},{"HotelId":"4649376","CityId":"129601","HotelName":"Optima Almaty"},{"HotelId":"4832710","CityId":"129601","HotelName":"Samal Resort And Spa"},{"HotelId":"4847662","CityId":"129601","HotelName":"Saraichik"},{"HotelId":"4900968","CityId":"129601","HotelName":"Grand Erbil Hotel"},{"HotelId":"5558360","CityId":"129601","HotelName":"Grand Hotel Eurasia"},{"HotelId":"6331503","CityId":"129601","HotelName":"Zyliha"},{"HotelId":"6499561","CityId":"129601","HotelName":"Uyut Hotel"},{"HotelId":"7941487","CityId":"129601","HotelName":"Lequipage Hotel"},{"HotelId":"9953122","CityId":"129601","HotelName":"Aksunkar Hotel"},{"HotelId":"10945188","CityId":"129601","HotelName":"City Hotel Tien Shan"},{"HotelId":"10946057","CityId":"129601","HotelName":"Hotel Mildom Express"},{"HotelId":"11892425","CityId":"129601","HotelName":"Mercure Almaty City Center"},{"HotelId":"11960695","CityId":"129601","HotelName":"Business Hotel Almaty"},{"HotelId":"12695361","CityId":"129601","HotelName":"Hotel Relax"},{"HotelId":"15685633","CityId":"129601","HotelName":"Renion Hills Hotel"},{"HotelId":"15932302","CityId":"129601","HotelName":"Shymbulak Resort Hotel"},{"HotelId":"17622090","CityId":"129601","HotelName":"Hotel Keremet"},{"HotelId":"26821506","CityId":"129601","HotelName":"Iris Hotel"},{"HotelId":"29636779","CityId":"129601","HotelName":"Nice Hostel"},{"HotelId":"31816140","CityId":"129601","HotelName":"Salut Hotel Almaty"},{"HotelId":"33866766","CityId":"129601","HotelName":"Oi-Qaragai Lesnaya Skazka"},{"HotelId":"35997896","CityId":"129601","HotelName":"Les Hostel"},{"HotelId":"36460631","CityId":"129601","HotelName":"DoubleTree by Hilton Almaty"},{"HotelId":"38282674","CityId":"129601","HotelName":"Maqan Hotel Almaty"},{"HotelId":"41338509","CityId":"129601","HotelName":"Royal Plus Hotel"},{"HotelId":"41341627","CityId":"129601","HotelName":"Resident Hotel Almaty"},{"HotelId":"42793184","CityId":"129601","HotelName":"Hotel Tahar"},{"HotelId":"42914313","CityId":"129601","HotelName":"Hotel Kazakhfilm"},{"HotelId":"44358880","CityId":"129601","HotelName":"Beis Spa Hotel Resort"},{"HotelId":"44876715","CityId":"129601","HotelName":"Golden Mir Hotel & Spa"},{"HotelId":"44947771","CityId":"129601","HotelName":"My Hostel Almaty"},{"HotelId":"48389255","CityId":"129601","HotelName":"The Plaza Hotel"},{"HotelId":"48834821","CityId":"129601","HotelName":"Friendsbook.kz"},{"HotelId":"52701401","CityId":"129601","HotelName":"Mildom City Hotel"},{"HotelId":"53658659","CityId":"129601","HotelName":"Turkestan"},{"HotelId":"54857507","CityId":"129601","HotelName":"Sacvoyage Hotel"},{"HotelId":"55130001","CityId":"129601","HotelName":"Novotel Almaty City Center"},{"HotelId":"59480674","CityId":"129601","HotelName":"Ramada Almaty"},{"HotelId":"59659872","CityId":"129601","HotelName":"Mika City Hotel"},{"HotelId":"61970753","CityId":"129601","HotelName":"Resident Hotel Delux"},{"HotelId":"70236327","CityId":"129601","HotelName":"Donatello Boutique"},{"HotelId":"71142348","CityId":"129601","HotelName":"Medeu Hotel Almaty"},{"HotelId":"73635643","CityId":"129601","HotelName":"Rahat Palace"},{"HotelId":"74870933","CityId":"129601","HotelName":"Grand Sapphire Hotel"},{"HotelId":"76115633","CityId":"129601","HotelName":"Business Hotel Almaty"},{"HotelId":"82072131","CityId":"129601","HotelName":"Hotel Grand Voyage"},{"HotelId":"83592880","CityId":"129601","HotelName":"Alma"},{"HotelId":"83710871","CityId":"129601","HotelName":"Olympica Hotel"},{"HotelId":"84735533","CityId":"129601","HotelName":"Almaty Five Seasons Hotel&Hostel"},{"HotelId":"85148990","CityId":"129601","HotelName":"Edelweiss Hotel"},{"HotelId":"85876856","CityId":"129601","HotelName":"Mini Inn Royal Orsep"},{"HotelId":"86104840","CityId":"129601","HotelName":"KaAiEr"},{"HotelId":"87405703","CityId":"129601","HotelName":"Garden Park Inn"},{"HotelId":"94342320","CityId":"129601","HotelName":"Shera Park Inn"},{"HotelId":"94801571","CityId":"129601","HotelName":"World Travelers Hostel"},{"HotelId":"97731523","CityId":"129601","HotelName":"InterContinental Almaty"},{"HotelId":"73953651","CityId":"131707","HotelName":"Arai Plaza Hotel"},{"HotelId":"70805469","CityId":"156567","HotelName":"Nurtau"},{"HotelId":"2740286","CityId":"205191","HotelName":"Hotel Aner"},{"HotelId":"4405592","CityId":"205191","HotelName":"Union Plaza"},{"HotelId":"7486448","CityId":"205191","HotelName":"Brown Hotel"},{"HotelId":"9746918","CityId":"205191","HotelName":"The One Hotel Astana"},{"HotelId":"18021284","CityId":"205191","HotelName":"Hotel Botakoz"},{"HotelId":"20625506","CityId":"205191","HotelName":"Business Hotel Astana"},{"HotelId":"20729641","CityId":"205191","HotelName":"Gostinitsa Daniyar"},{"HotelId":"20760922","CityId":"205191","HotelName":"Lion"},{"HotelId":"25283232","CityId":"205191","HotelName":"Maxx Inn"},{"HotelId":"32445850","CityId":"205191","HotelName":"Baiterek Premium"},{"HotelId":"33382488","CityId":"205191","HotelName":"Rauan Hotel"},{"HotelId":"44074204","CityId":"205191","HotelName":"Traditional Hotel"},{"HotelId":"47601910","CityId":"205191","HotelName":"Azat"},{"HotelId":"53635403","CityId":"205191","HotelName":"Nursat Guest House"},{"HotelId":"53739127","CityId":"205191","HotelName":"Sheraton Nur-Sultan Hotel"},{"HotelId":"53864161","CityId":"205191","HotelName":"Myrza"},{"HotelId":"54694742","CityId":"205191","HotelName":"Mini Hotel Pulsar"},{"HotelId":"61928834","CityId":"205191","HotelName":"Grace Point Hotel"},{"HotelId":"62264953","CityId":"205191","HotelName":"Sky Luxe Hotel"},{"HotelId":"78634471","CityId":"205191","HotelName":"The Arc Residence"},{"HotelId":"85097017","CityId":"205191","HotelName":"Ulpan Guest House"},{"HotelId":"90517839","CityId":"205191","HotelName":"Belon Life Hotel"},{"HotelId":"92774515","CityId":"205191","HotelName":"Elite Apartments Highvill"},{"HotelId":"95852987","CityId":"205191","HotelName":"The Square"},{"HotelId":"1935082","CityId":"307589","HotelName":"Inn Ozz"},{"HotelId":"20856972","CityId":"307589","HotelName":"Dostar-Alem Hotel"},{"HotelId":"22314847","CityId":"307589","HotelName":"Voyage Hotel & Restaurant"},{"HotelId":"25442856","CityId":"307589","HotelName":"Hotel Ar Nuvo"},{"HotelId":"37198026","CityId":"307589","HotelName":"Hotel Zumrat"},{"HotelId":"37299002","CityId":"307589","HotelName":"Hotel Meridian"},{"HotelId":"41241100","CityId":"307589","HotelName":"Park Hotel"},{"HotelId":"41771580","CityId":"307589","HotelName":"Apart Hotel 92\/2"},{"HotelId":"52586796","CityId":"307589","HotelName":"Hotel Somplex Ak-Zhaik"},{"HotelId":"61733423","CityId":"307589","HotelName":"Edem"},{"HotelId":"63489221","CityId":"307589","HotelName":"Hotel Senator"},{"HotelId":"84405278","CityId":"307589","HotelName":"Metelitsa Hotel"},{"HotelId":"99999455","CityId":"377198","HotelName":"Park House Kokshetau"},{"HotelId":"2586492","CityId":"413905","HotelName":"Rakhat Hotel"},{"HotelId":"9496712","CityId":"413905","HotelName":"Chagala Hotel Uralsk"},{"HotelId":"31108722","CityId":"413905","HotelName":"Pushkin"},{"HotelId":"69551459","CityId":"413905","HotelName":"Aparthotel Vegus"},{"HotelId":"71055753","CityId":"413905","HotelName":"Victoria Hotel"},{"HotelId":"8481504","CityId":"421872","HotelName":"Hotel Irtysh"},{"HotelId":"25779088","CityId":"427969","HotelName":"Yamayka Beach Resort"},{"HotelId":"9278996","CityId":"431406","HotelName":"Altyn Adam Hotel"},{"HotelId":"27934904","CityId":"431406","HotelName":"Hotel Complex Skif"},{"HotelId":"7722329","CityId":"446613","HotelName":"Celinnaya"},{"HotelId":"24341927","CityId":"446613","HotelName":"Medeu"},{"HotelId":"28688211","CityId":"446613","HotelName":"Palazzo Hotel"},{"HotelId":"56445672","CityId":"446613","HotelName":"Gostinichnyy Kompleks Tobol"},{"HotelId":"61018051","CityId":"446613","HotelName":"Ostrov Hotel"},{"HotelId":"88009255","CityId":"446613","HotelName":"Hotel Fessla"},{"HotelId":"1156266","CityId":"455669","HotelName":"Rixos President Astana"},{"HotelId":"1357994","CityId":"455669","HotelName":"Beijing Palace Soluxe"},{"HotelId":"1646357","CityId":"455669","HotelName":"Park Inn by Radisson Astana"},{"HotelId":"1760927","CityId":"455669","HotelName":"Oasis Inn"},{"HotelId":"1800555","CityId":"455669","HotelName":"Comfort Hotel Astana"},{"HotelId":"1867967","CityId":"455669","HotelName":"Mukammal"},{"HotelId":"1941760","CityId":"455669","HotelName":"Almaty"},{"HotelId":"1975775","CityId":"455669","HotelName":"Kazzhol Astana"},{"HotelId":"2096955","CityId":"455669","HotelName":"Duman"},{"HotelId":"2324830","CityId":"455669","HotelName":"Diplomat"},{"HotelId":"2418170","CityId":"455669","HotelName":"G Empire"},{"HotelId":"3186270","CityId":"455669","HotelName":"Hilton Garden Inn Astana"},{"HotelId":"3263806","CityId":"455669","HotelName":"O Azamat"},{"HotelId":"3360707","CityId":"455669","HotelName":"Astana Marriott Hotel"},{"HotelId":"3756480","CityId":"455669","HotelName":"Manhattan"},{"HotelId":"3956376","CityId":"455669","HotelName":"Goldman Empire"},{"HotelId":"4132850","CityId":"455669","HotelName":"King"},{"HotelId":"4217737","CityId":"455669","HotelName":"Radisson Hotel Astana"},{"HotelId":"4247223","CityId":"455669","HotelName":"Tengri"},{"HotelId":"5090527","CityId":"455669","HotelName":"Altyn Dala Hotel"},{"HotelId":"5601088","CityId":"455669","HotelName":"Royal Park Astana"},{"HotelId":"5756182","CityId":"455669","HotelName":"Grand Park Esil"},{"HotelId":"6088413","CityId":"455669","HotelName":"Red Village Hotel"},{"HotelId":"6418082","CityId":"455669","HotelName":"Tri Peskarya"},{"HotelId":"7536400","CityId":"455669","HotelName":"Metro Park Hotel"},{"HotelId":"8266031","CityId":"455669","HotelName":"Green Which Hotel Borovoe"},{"HotelId":"10348685","CityId":"455669","HotelName":"Jumbaktas"},{"HotelId":"10889375","CityId":"455669","HotelName":"Altyn-Adam Hotel"},{"HotelId":"11101527","CityId":"455669","HotelName":"Park Hotel Kokshetau"},{"HotelId":"11461528","CityId":"455669","HotelName":"Prestige"},{"HotelId":"13211600","CityId":"455669","HotelName":"Hotel Monaco"},{"HotelId":"15113233","CityId":"455669","HotelName":"Alanda Hotel"},{"HotelId":"18131293","CityId":"455669","HotelName":"Best Western Plus Astana"},{"HotelId":"20284253","CityId":"455669","HotelName":"Hotel Zhansaya"},{"HotelId":"21754931","CityId":"455669","HotelName":"Orynbor Boutique-Hotel"},{"HotelId":"23005692","CityId":"455669","HotelName":"Qonaq Hotel"},{"HotelId":"26730841","CityId":"455669","HotelName":"Brown Hotel"},{"HotelId":"27140349","CityId":"455669","HotelName":"Jelsomino Boutique Hotel"},{"HotelId":"29041518","CityId":"455669","HotelName":"The St. Regis Astana"},{"HotelId":"32395172","CityId":"455669","HotelName":"Hampton by Hilton Astana Triumphal Arch"},{"HotelId":"34957830","CityId":"455669","HotelName":"ibis Astana"},{"HotelId":"45723073","CityId":"455669","HotelName":"San Marino Hotel Astana"},{"HotelId":"48221338","CityId":"455669","HotelName":"Hotel Tourist"},{"HotelId":"52905858","CityId":"455669","HotelName":"Azamat Hotel"},{"HotelId":"54900334","CityId":"455669","HotelName":"Wyndham Garden Astana"},{"HotelId":"62648632","CityId":"455669","HotelName":"Hotel Absolute"},{"HotelId":"67272831","CityId":"455669","HotelName":"Holiday Inn Express Astana - Turan"},{"HotelId":"67705395","CityId":"455669","HotelName":"Bon Mary New Hostel"},{"HotelId":"67783987","CityId":"455669","HotelName":"Lion"},{"HotelId":"67902060","CityId":"455669","HotelName":"The Ritz-Carlton Astana"},{"HotelId":"68550532","CityId":"455669","HotelName":"Belon Lux"},{"HotelId":"70124191","CityId":"455669","HotelName":"Hilton Astana"},{"HotelId":"70582814","CityId":"455669","HotelName":"Rixos Borovoe"},{"HotelId":"73259421","CityId":"455669","HotelName":"Shanyrak On Abaya"},{"HotelId":"80147442","CityId":"455669","HotelName":"Inn Sofia"},{"HotelId":"86031045","CityId":"455669","HotelName":"Boutique Hotel Tomiris"},{"HotelId":"86954329","CityId":"455669","HotelName":"Discovery Borovoe"},{"HotelId":"89188546","CityId":"455669","HotelName":"Astana Central Hotel"},{"HotelId":"89201415","CityId":"455669","HotelName":"East Astana Hotel"},{"HotelId":"90150701","CityId":"455669","HotelName":"Versal Hotel"},{"HotelId":"97797431","CityId":"455669","HotelName":"Eco Apart Hotel"},{"HotelId":"98127667","CityId":"455669","HotelName":"Bon Mary Apart Hotel"},{"HotelId":"98293261","CityId":"455669","HotelName":"Astana Central Hotel"},{"HotelId":"26689512","CityId":"464840","HotelName":"Royal Petrol"},{"HotelId":"46974722","CityId":"464840","HotelName":"Koktem Grand"},{"HotelId":"1434325","CityId":"488004","HotelName":"Renaissance Aktau"},{"HotelId":"3081523","CityId":"488004","HotelName":"Chagala Hotel"},{"HotelId":"9246716","CityId":"488004","HotelName":"Grand Hotel Victory"},{"HotelId":"9344292","CityId":"488004","HotelName":"Silk Way Hotel"},{"HotelId":"32750450","CityId":"488004","HotelName":"Caspian Riviera Grand Palace"},{"HotelId":"36613780","CityId":"488004","HotelName":"Aktau Hotel"},{"HotelId":"54590150","CityId":"488004","HotelName":"Rahat Hotel"},{"HotelId":"67670324","CityId":"488004","HotelName":"Holiday Inn Aktau - Seaside"},{"HotelId":"87680541","CityId":"488004","HotelName":"Holiday Inn Aktau"},{"HotelId":"96944653","CityId":"488004","HotelName":"Dostar Hotel Complex"},{"HotelId":"99586635","CityId":"488004","HotelName":"Zhanaotel Hotel"},{"HotelId":"4712111","CityId":"493135","HotelName":"Dastan Aktobe"},{"HotelId":"10283294","CityId":"493135","HotelName":"Ilek Hotel"},{"HotelId":"79616082","CityId":"493135","HotelName":"ibis Aktobe"},{"HotelId":"86042619","CityId":"493135","HotelName":"Amsterdam Hotel Aktobe"},{"HotelId":"87113675","CityId":"493135","HotelName":"Hotel Arai"},{"HotelId":"7366174","CityId":"535295","HotelName":"Aidana Plaza Hotel"},{"HotelId":"12783644","CityId":"535295","HotelName":"Canvas"},{"HotelId":"24106052","CityId":"535295","HotelName":"Shymkent Hotel"},{"HotelId":"27802872","CityId":"535295","HotelName":"Promenade Park Hotel"},{"HotelId":"33609859","CityId":"535295","HotelName":"Express City Hotel"},{"HotelId":"34469538","CityId":"535295","HotelName":"Ramada by Wyndham Shymkent"},{"HotelId":"52764596","CityId":"535295","HotelName":"Dostyk"},{"HotelId":"62955717","CityId":"535295","HotelName":"Orda Hotel"},{"HotelId":"73859940","CityId":"535295","HotelName":"Megapolis Hotel Shymkent"},{"HotelId":"79415001","CityId":"535295","HotelName":"Rixos Khadisha Shymkent"},{"HotelId":"82984589","CityId":"535295","HotelName":"Kainar Hotel"},{"HotelId":"93818856","CityId":"535295","HotelName":"Orbita Boutique Hotel"},{"HotelId":"2501705","CityId":"644707","HotelName":"Marko Polo Aksay Hotel"},{"HotelId":"26775721","CityId":"644707","HotelName":"Aksai Residence"},{"HotelId":"76643983","CityId":"644707","HotelName":"Chagala Hotel Aksai"},{"HotelId":"5017914","CityId":"695897","HotelName":"Plaza Hotel"},{"HotelId":"37951315","CityId":"695897","HotelName":"Dostyk Hotel"},{"HotelId":"45914909","CityId":"695897","HotelName":"Green Which Hotel"},{"HotelId":"52077278","CityId":"734917","HotelName":"Cosmonaut Hotel"},{"HotelId":"7060881","CityId":"783530","HotelName":"Nomad Palace"},{"HotelId":"21974041","CityId":"783530","HotelName":"Sultan Plaza Hotel"},{"HotelId":"38625154","CityId":"783530","HotelName":"Hotel Mereke"},{"HotelId":"1331619","CityId":"799621","HotelName":"Atyrau Dastan Hotel"},{"HotelId":"4241970","CityId":"799621","HotelName":"Ardager Residence"},{"HotelId":"19855014","CityId":"799621","HotelName":"Residence Keruen"},{"HotelId":"25530304","CityId":"799621","HotelName":"Marriott Executive Apartments Atyrau"},{"HotelId":"30163553","CityId":"799621","HotelName":"Renaissance Atyrau"},{"HotelId":"40634406","CityId":"799621","HotelName":"Chagala Residences Atyrau"},{"HotelId":"45211850","CityId":"799621","HotelName":"Hotel Sunkar"},{"HotelId":"57938082","CityId":"799621","HotelName":"Kazakhstan Hotel"},{"HotelId":"58596066","CityId":"799621","HotelName":"Infinity Plaza Hotel"},{"HotelId":"64597289","CityId":"799621","HotelName":"River Palace"},{"HotelId":"71031316","CityId":"799621","HotelName":"Laeti Hotel"},{"HotelId":"72610720","CityId":"799621","HotelName":"Chagala Atyrau Hotel"},{"HotelId":"80893029","CityId":"799621","HotelName":"Sultan Palace Hotel"},{"HotelId":"86198118","CityId":"799621","HotelName":"Tengri Hotel"},{"HotelId":"92374874","CityId":"799621","HotelName":"Green Hotel"},{"HotelId":"98449592","CityId":"799621","HotelName":"Victoria Palace"},{"HotelId":"71455041","CityId":"926556","HotelName":"Semey Hotel"},{"HotelId":"6725334","CityId":"962991","HotelName":"Dedeman Oskemen Tavros"},{"HotelId":"22199154","CityId":"962991","HotelName":"City Hotel"},{"HotelId":"34463586","CityId":"962991","HotelName":"De Luxe Hotel"},{"HotelId":"51013954","CityId":"962991","HotelName":"Ust-Kamenogorsk Hotel"},{"HotelId":"64088313","CityId":"962991","HotelName":"Shiny River Hotel"},{"HotelId":"78608101","CityId":"962991","HotelName":"GALIRAD Hotel"}]}}}