{"Head":{"ServerTime":"2021-06-12T13:16:46","ServerType":"Test","ResponseType":"GetHotels","ExecutionTime":"0.024"},"Body":{"HotelsReturned":"48","Hotels":{"Hotel":[{"HotelId":"1622620","CityId":"247347","HotelName":"Best Western Gobi\u00b4s Kelso Hotel"},{"HotelId":"3279315","CityId":"247347","HotelName":"Kempinski Hotel Khan Palace"},{"HotelId":"4342501","CityId":"247347","HotelName":"Ramada Ulaanbaatar City Center"},{"HotelId":"4652369","CityId":"247347","HotelName":"HS Khaan Resort Hotel"},{"HotelId":"4910304","CityId":"247347","HotelName":"The Blue Sky Hotel & Tower"},{"HotelId":"9946738","CityId":"247347","HotelName":"Chinggis Khaan"},{"HotelId":"12829621","CityId":"247347","HotelName":"The Continental Hotel"},{"HotelId":"22356812","CityId":"247347","HotelName":"Platinum Hotel"},{"HotelId":"22563304","CityId":"247347","HotelName":"Bishrelt"},{"HotelId":"23726448","CityId":"247347","HotelName":"Novotel Ulaanbaatar"},{"HotelId":"23951713","CityId":"247347","HotelName":"Elegance Hotel"},{"HotelId":"27531218","CityId":"247347","HotelName":"Mongolian Vision Tours"},{"HotelId":"29300076","CityId":"247347","HotelName":"Mika"},{"HotelId":"31290274","CityId":"247347","HotelName":"Alpha Hotel Mongolia"},{"HotelId":"31710332","CityId":"247347","HotelName":"Urgoo hotel"},{"HotelId":"32203358","CityId":"247347","HotelName":"Zolo Hotel"},{"HotelId":"33068283","CityId":"247347","HotelName":"Tsetsen Khangai Hotel"},{"HotelId":"33407671","CityId":"247347","HotelName":"New West Hotel"},{"HotelId":"33586916","CityId":"247347","HotelName":"Premium Hotel Ulaanbaatar"},{"HotelId":"34987366","CityId":"247347","HotelName":"Springs Hotel Ulaanbaatar"},{"HotelId":"35606034","CityId":"247347","HotelName":"Shangri-La Ulaanbaatar"},{"HotelId":"35767660","CityId":"247347","HotelName":"Kaiser"},{"HotelId":"35933174","CityId":"247347","HotelName":"Holiday Inn Ulaanbaater"},{"HotelId":"36097772","CityId":"247347","HotelName":"Best Western Premier Tuushin Hotel"},{"HotelId":"36174668","CityId":"247347","HotelName":"Sara's Guest House"},{"HotelId":"36992022","CityId":"247347","HotelName":"Zuchi Hotel"},{"HotelId":"39804559","CityId":"247347","HotelName":"Ibis Styles Ulaanbaatar Polaris"},{"HotelId":"40351205","CityId":"247347","HotelName":"Travel Mongolia Guesthouse"},{"HotelId":"45838251","CityId":"247347","HotelName":"Tanan Center"},{"HotelId":"50675175","CityId":"247347","HotelName":"Bayangol Hotel"},{"HotelId":"53237436","CityId":"247347","HotelName":"Land Hotel"},{"HotelId":"57554256","CityId":"247347","HotelName":"Puma Imperial Hotel"},{"HotelId":"60153808","CityId":"247347","HotelName":"H9 Hotel Nine Ulaanbaatar"},{"HotelId":"61253229","CityId":"247347","HotelName":"Ulaanbaatar"},{"HotelId":"61511445","CityId":"247347","HotelName":"UBINN Hotel & Gallery"},{"HotelId":"66829973","CityId":"247347","HotelName":"Khuvsgul Lake Hotel & Hostel"},{"HotelId":"68164216","CityId":"247347","HotelName":"The Grand Hill"},{"HotelId":"71517921","CityId":"247347","HotelName":"The Corporate Hotel Ulaanbaatar"},{"HotelId":"72546651","CityId":"247347","HotelName":"Flower Hotel"},{"HotelId":"75571136","CityId":"247347","HotelName":"Narantuul Hotel"},{"HotelId":"80115385","CityId":"247347","HotelName":"White House Hotel"},{"HotelId":"87752855","CityId":"247347","HotelName":"Toyoko Inn Ulaanbaatar"},{"HotelId":"90713522","CityId":"247347","HotelName":"The Corporate Hotel & Convention Centre"},{"HotelId":"92441433","CityId":"247347","HotelName":"Royal House Hotel"},{"HotelId":"95448834","CityId":"247347","HotelName":"UB City Hotel"},{"HotelId":"98082652","CityId":"247347","HotelName":"Okay Tours & Hostel"},{"HotelId":"98965791","CityId":"247347","HotelName":"Mika"},{"HotelId":"99971129","CityId":"247347","HotelName":"Royal House Hotel 2"}]}}}